cerebro/__init__.py
cerebro/__main__.py
cerebro/cerebro.py
cerebro/client.py
cerebro/observer.py
cerebro/protocols.py
cerebro/tools.py
cerebro/etc/cerebro.yaml
cerebro/sources/AMQP.py
cerebro/sources/__init__.py
cerebro/sources/drift.py
cerebro/sources/lco.py
cerebro/sources/lvm.py
cerebro/sources/source.py
cerebro/sources/tpm.py
cerebro/sources/tron.py
sdss_cerebro-1.3.2.dist-info/METADATA
sdss_cerebro-1.3.2.dist-info/WHEEL
sdss_cerebro-1.3.2.dist-info/entry_points.txt
sdss_cerebro-1.3.2.dist-info/licenses/LICENSE.md
sdss_cerebro-1.3.2.dist-info/RECORD
