Metadata-Version: 2.4
Name: sdss-cerebro
Version: 1.3.2
Summary: Telemetry management and time series for SDSS-V
Project-URL: Homepage, https://github.com/sdss/cerebro
Project-URL: Repository, https://github.com/sdss/cerebro
Project-URL: Documentation, https://sdss-cerebro.readthedocs.io/en/latest/
Author-email: José Sánchez-Gallego <gallegoj@uw.edu>
License-Expression: BSD-3-Clause
License-File: LICENSE.md
Requires-Python: <4,>=3.10
Requires-Dist: asyncudp>=0.11.0
Requires-Dist: click-default-group>=1.2.2
Requires-Dist: click>=8.0.0
Requires-Dist: daemonocle>=1.0.2
Requires-Dist: httpx>=0.28.1
Requires-Dist: influxdb-client[extra]>=1.9.0
Requires-Dist: lvmopstools>=0.5.7
Requires-Dist: ntplib>=0.3.4
Requires-Dist: numpy<2.3.0,>=2.0.0
Requires-Dist: peewee>=3.15.4
Requires-Dist: pymysql>=1.0.2
Requires-Dist: rx>=3.2.0
Requires-Dist: sdss-clu>=2.0.0
Requires-Dist: sdss-drift>=1.2.0
Requires-Dist: sdss-tpm-multicast-client>=0.3.0
Requires-Dist: sdsstools>=1.9.1
